iceportal_apis/__init__.py
iceportal_apis/constants.py
iceportal_apis/exceptions.py
iceportal_apis/types.py
iceportal_apis-2.0.3.dist-info/LICENSE
iceportal_apis-2.0.3.dist-info/METADATA
iceportal_apis-2.0.3.dist-info/WHEEL
iceportal_apis-2.0.3.dist-info/top_level.txt
iceportal_apis-2.0.3.dist-info/RECORD
