Metadata-Version: 2.1
Name: iceportal_apis
Version: 2.0.3
Summary: A module for interacting with the Deutsche Bahn onboard APIs
Home-page: https://github.com/felix-zenk/iceportal-apis
Author: Felix Zenk
Author-email: felix.zenk@web.de
License: MIT
Project-URL: Bug Reports, https://github.com/felix-zenk/iceportal-apis/issues/new?labels=bug&template=bug_report.md&title=%5BBUG%5D%3A+
Project-URL: Source, https://github.com/felix-zenk/iceportal-apis
Classifier: License :: OSI Approved :: MIT License
Classifier: Operating System :: OS Independent
Classifier: Programming Language :: Python :: 3
Classifier: Programming Language :: Python :: 3.6
Classifier: Programming Language :: Python :: 3.7
Classifier: Programming Language :: Python :: 3.8
Classifier: Programming Language :: Python :: 3.9
Classifier: Programming Language :: Python :: 3.10
Classifier: License :: OSI Approved :: MIT License
Classifier: Operating System :: OS Independent
Classifier: Topic :: Internet :: WWW/HTTP :: Dynamic Content
Classifier: Topic :: Utilities
Requires-Python: >=3.8
License-File: LICENSE
